automorphotrack/__init__.py
automorphotrack/colocalization.py
automorphotrack/detection.py
automorphotrack/lyso_count.py
automorphotrack/morphology.py
automorphotrack/motility.py
automorphotrack/shape_features.py
automorphotrack/shape_profiling.py
automorphotrack/summary.py
automorphotrack/tracking.py
automorphotrack/tracking_overlay.py
automorphotrack/utils.py
automorphotrack-1.0.5.dist-info/licenses/LICENSE.md
automorphotrack-1.0.5.dist-info/METADATA
automorphotrack-1.0.5.dist-info/WHEEL
automorphotrack-1.0.5.dist-info/top_level.txt
automorphotrack-1.0.5.dist-info/RECORD
