Metadata-Version: 2.4
Name: AutoMorphoTrack
Version: 1.0.5
Summary: AutoMorphoTrack is an open-source Python package for automated detection, morphology classification, motility tracking, and colocalization analysis of organelles in multichannel fluorescence microscopy data.
Home-page: https://github.com/abayatibrain/AMTpackage
Author: Armin Bayati
Author-email: a.bayati.brain@gmail.com
License: MIT
Project-URL: Documentation, https://github.com/abayatibrain/AMTpackage
Project-URL: Source, https://github.com/abayatibrain/AMTpackage
Project-URL: Tracker, https://github.com/abayatibrain/AMTpackage/issues
Classifier: Programming Language :: Python :: 3
Classifier: License :: OSI Approved :: MIT License
Classifier: Operating System :: OS Independent
Classifier: Intended Audience :: Science/Research
Classifier: Topic :: Scientific/Engineering :: Image Processing
Requires-Python: >=3.9
License-File: LICENSE.md
Requires-Dist: numpy>=1.23.0
Requires-Dist: pandas>=1.5.0
Requires-Dist: matplotlib>=3.6.0
Requires-Dist: seaborn>=0.12.0
Requires-Dist: opencv-python>=4.6.0
Requires-Dist: scikit-image>=0.19.0
Requires-Dist: scipy>=1.9.0
Requires-Dist: tifffile>=2022.8.12
Dynamic: author
Dynamic: author-email
Dynamic: classifier
Dynamic: description
Dynamic: description-content-type
Dynamic: home-page
Dynamic: license
Dynamic: license-file
Dynamic: project-url
Dynamic: requires-dist
Dynamic: requires-python
Dynamic: summary
